{"appDisplayName":"Leave Management_202604100859","description":"Employee leave request and approval system with manager dashboards","buildPath":"./dist","buildEntryPoint":"index.html","logoPath":"Default","localAppUrl":"http://localhost:5173/","appId":"bbf9fbdd-727e-49fd-ae98-34d2cd1c5611","connectionReferences":{},"databaseReferences":{"default.cds":{"databaseDetails":{"environmentName":"default.cds","referenceType":"Environmental","linkedEnvironmentMetadata":{"resourceId":"6cd3d694-952e-f111-afc0-6045bde84ad6","friendlyName":"trial-ind-d962717f","uniqueName":"unq6cd3d694952ef111afc06045bde84","domainName":"org428c2773","version":"9.2.26034.160","instanceUrl":"https://org428c2773.crm8.dynamics.com/","instanceApiUrl":"https://org428c2773.api.crm8.dynamics.com","baseLanguage":1033,"instanceState":"Ready","createdTime":"2026-04-02T13:23:39.437Z","platformSku":"Standard"}},"dataSources":{"crdb0_leaverequest":{"entitySetName":"crdb0_leaverequests","logicalName":"crdb0_leaverequest","isHidden":false},"crdb0_leavebalance":{"entitySetName":"crdb0_leavebalances","logicalName":"crdb0_leavebalance","isHidden":false},"crdb0_employee":{"entitySetName":"crdb0_employees","logicalName":"crdb0_employee","isHidden":false}}}}}